pyeau/__init__.py
pyeau/abc/__init__.py
pyeau/abc/abstract_view.py
pyeau/abc/group.py
pyeau/abc/sprite.py
pyeau/utils/__init__.py
pyeau/utils/loader_old.py
pyeau-0.1.0.dist-info/METADATA
pyeau-0.1.0.dist-info/WHEEL
pyeau-0.1.0.dist-info/licenses/LICENSE
pyeau-0.1.0.dist-info/RECORD
