Metadata-Version: 2.1
Name: pyeau
Version: 0.1.0
Summary: AramEaus pygame ABC implementation
Project-URL: Homepage, https://github.com/Aram-Eau/pyeau
Project-URL: Download Page, https://scpup-game.web.app
Author-email: Ivan Aram Gonzalez Su <ivan.ags.95@gmail.com>
License-File: LICENSE
Classifier: License :: OSI Approved :: MIT License
Classifier: Operating System :: Microsoft :: Windows
Classifier: Programming Language :: Python :: 3
Requires-Python: >=3.9
Requires-Dist: pygame<=2.5.1,>=2.0.1
